container_scheduler/__init__.py
container_scheduler/container_scheduler.py
container_scheduler/graceful_halt_signal_receiver.py
container_scheduler-1.0.0.dist-info/LICENSE.txt
container_scheduler-1.0.0.dist-info/METADATA
container_scheduler-1.0.0.dist-info/WHEEL
container_scheduler-1.0.0.dist-info/top_level.txt
container_scheduler-1.0.0.dist-info/RECORD
