Metadata-Version: 2.1
Name: container-scheduler
Version: 1.0.0
Summary: A scheduler for docker containers, made easy
Author-email: Yusef Maali <contact@yusefmaali.net>
License: MIT
Project-URL: homepage, https://github.com/yusefmaali/container-scheduler
Project-URL: repository, https://github.com/yusefmaali/container-scheduler
Project-URL: changelog, https://github.com/yusefmaali/container-scheduler/blob/master/CHANGELOG.rst
Project-URL: download, https://github.com/yusefmaali/container-scheduler/tarball/1.0.0
Keywords: docker,container,schedule,container scheduler,schedule container,docker container scheduler,periodic,scheduling,clockwork,cron,scheduler,job scheduling,cronjob,cronjob scheduling
Classifier: Intended Audience :: Developers
Classifier: License :: OSI Approved :: MIT License
Classifier: Development Status :: 5 - Production/Stable
Classifier: Operating System :: OS Independent
Classifier: Programming Language :: Python
Classifier: Programming Language :: Python :: 3
Classifier: Programming Language :: Python :: 3.7
Classifier: Programming Language :: Python :: 3.8
Classifier: Programming Language :: Python :: 3.9
Classifier: Programming Language :: Python :: 3.10
Classifier: Programming Language :: Python :: 3.11
Classifier: Natural Language :: English
Requires-Python: >=3.7
License-File: LICENSE.txt
Requires-Dist: docker ~=6.0
Requires-Dist: schedule-cronjob ~=1.0
